dsharp/__init__.py
dsharp/file.py
dsharp/log.py
dsharp/math.py
dsharp-0.0.3.dist-info/licenses/LICENSE
dsharp-0.0.3.dist-info/METADATA
dsharp-0.0.3.dist-info/WHEEL
dsharp-0.0.3.dist-info/top_level.txt
dsharp-0.0.3.dist-info/RECORD
