Metadata-Version: 2.4
Name: dsharp
Version: 0.0.3
Summary: A programming language made in python
Author-email: ChipDev <skylertruitt6655@gmail.com>
License-Expression: MIT
Project-URL: Docs, https://sites.google.com/view/dsharp/syntaxes
Classifier: Programming Language :: Python :: 3
Classifier: Operating System :: OS Independent
Requires-Python: >=3.9
License-File: LICENSE
Dynamic: license-file
